{
"meta":{"test_sets":[],"test_metrics":[],"learn_metrics":[{"best_value":"Min","name":"RMSE"}],"launch_mode":"Train","parameters":"","iteration_count":100,"learn_sets":["learn"],"name":"experiment"},
"iterations":[
{"learn":[14.005006],"iteration":0,"passed_time":0.0007823375229,"remaining_time":0.07745141477},
{"learn":[13.14441192],"iteration":1,"passed_time":0.001478417553,"remaining_time":0.0724424601},
{"learn":[12.34258257],"iteration":2,"passed_time":0.002140063069,"remaining_time":0.06919537256},
{"learn":[11.64527793],"iteration":3,"passed_time":0.00262120158,"remaining_time":0.06290883792},
{"learn":[11.02766183],"iteration":4,"passed_time":0.003260800386,"remaining_time":0.06195520733},
{"learn":[10.43485794],"iteration":5,"passed_time":0.003889600927,"remaining_time":0.06093708119},
{"learn":[9.890641275],"iteration":6,"passed_time":0.004526808037,"remaining_time":0.0601418782},
{"learn":[9.492161212],"iteration":7,"passed_time":0.005126365922,"remaining_time":0.0589532081},
{"learn":[9.105082953],"iteration":8,"passed_time":0.005859718432,"remaining_time":0.05924826415},
{"learn":[8.674157135],"iteration":9,"passed_time":0.006617397673,"remaining_time":0.05955657906},
{"learn":[8.341743544],"iteration":10,"passed_time":0.007336572953,"remaining_time":0.0593595448},
{"learn":[8.049372916],"iteration":11,"passed_time":0.007997877791,"remaining_time":0.0586511038},
{"learn":[7.757318612],"iteration":12,"passed_time":0.008609679213,"remaining_time":0.05761862243},
{"learn":[7.522206899],"iteration":13,"passed_time":0.009242775596,"remaining_time":0.05677705009},
{"learn":[7.297756655],"iteration":14,"passed_time":0.009830547077,"remaining_time":0.05570643344},
{"learn":[7.088359431],"iteration":15,"passed_time":0.01043625628,"remaining_time":0.05479034547},
{"learn":[6.882113791],"iteration":16,"passed_time":0.01107080576,"remaining_time":0.05405158104},
{"learn":[6.704728832],"iteration":17,"passed_time":0.0116651179,"remaining_time":0.05314109266},
{"learn":[6.563881962],"iteration":18,"passed_time":0.01225360463,"remaining_time":0.05223905132},
{"learn":[6.418790279],"iteration":19,"passed_time":0.01285128097,"remaining_time":0.05140512387},
{"learn":[6.315756953],"iteration":20,"passed_time":0.01345140114,"remaining_time":0.05060289002},
{"learn":[6.210157751],"iteration":21,"passed_time":0.01400529693,"remaining_time":0.04965514365},
{"learn":[6.115058449],"iteration":22,"passed_time":0.01467555064,"remaining_time":0.04913119127},
{"learn":[6.014819884],"iteration":23,"passed_time":0.01529530671,"remaining_time":0.04843513791},
{"learn":[5.93117229],"iteration":24,"passed_time":0.01592492157,"remaining_time":0.04777476472},
{"learn":[5.844857622],"iteration":25,"passed_time":0.01671981681,"remaining_time":0.04758717091},
{"learn":[5.771145213],"iteration":26,"passed_time":0.01733826448,"remaining_time":0.0468775299},
{"learn":[5.704018229],"iteration":27,"passed_time":0.01798021414,"remaining_time":0.04623483636},
{"learn":[5.665806474],"iteration":28,"passed_time":0.01884162885,"remaining_time":0.04612950512},
{"learn":[5.616500369],"iteration":29,"passed_time":0.01952527589,"remaining_time":0.04555897707},
{"learn":[5.558023666],"iteration":30,"passed_time":0.0201811716,"remaining_time":0.04491938194},
{"learn":[5.510080976],"iteration":31,"passed_time":0.02084530962,"remaining_time":0.04429628295},
{"learn":[5.468747792],"iteration":32,"passed_time":0.02151289006,"remaining_time":0.04367768587},
{"learn":[5.429275534],"iteration":33,"passed_time":0.02215520299,"remaining_time":0.04300715874},
{"learn":[5.402117324],"iteration":34,"passed_time":0.02277762973,"remaining_time":0.04230131235},
{"learn":[5.367635151],"iteration":35,"passed_time":0.02341422848,"remaining_time":0.04162529508},
{"learn":[5.345181232],"iteration":36,"passed_time":0.02409766868,"remaining_time":0.04103116559},
{"learn":[5.319151269],"iteration":37,"passed_time":0.02475936286,"remaining_time":0.0403968552},
{"learn":[5.296134146],"iteration":38,"passed_time":0.02543381594,"remaining_time":0.03978109673},
{"learn":[5.269629003],"iteration":39,"passed_time":0.02611209296,"remaining_time":0.03916813944},
{"learn":[5.251147059],"iteration":40,"passed_time":0.02677864006,"remaining_time":0.03853511619},
{"learn":[5.248003302],"iteration":41,"passed_time":0.02707504525,"remaining_time":0.03738934821},
{"learn":[5.232376509],"iteration":42,"passed_time":0.02776912293,"remaining_time":0.03681023273},
{"learn":[5.213524255],"iteration":43,"passed_time":0.02848000854,"remaining_time":0.03624728359},
{"learn":[5.189691584],"iteration":44,"passed_time":0.0291352003,"remaining_time":0.03560968925},
{"learn":[5.166052198],"iteration":45,"passed_time":0.02981845712,"remaining_time":0.03500427575},
{"learn":[5.140406659],"iteration":46,"passed_time":0.030494737,"remaining_time":0.03438768215},
{"learn":[5.118929684],"iteration":47,"passed_time":0.0311935355,"remaining_time":0.03379299679},
{"learn":[5.108792602],"iteration":48,"passed_time":0.03191618577,"remaining_time":0.03321888723},
{"learn":[5.098141225],"iteration":49,"passed_time":0.0326214024,"remaining_time":0.0326214024},
{"learn":[5.085926393],"iteration":50,"passed_time":0.03330632176,"remaining_time":0.03200019149},
{"learn":[5.067816804],"iteration":51,"passed_time":0.0339432047,"remaining_time":0.03133218896},
{"learn":[5.049834901],"iteration":52,"passed_time":0.03460843689,"remaining_time":0.03069050064},
{"learn":[5.03838627],"iteration":53,"passed_time":0.03529206394,"remaining_time":0.03006361002},
{"learn":[5.033534248],"iteration":54,"passed_time":0.03577128353,"remaining_time":0.0292674138},
{"learn":[5.023726885],"iteration":55,"passed_time":0.03642603554,"remaining_time":0.02862045649},
{"learn":[5.01290392],"iteration":56,"passed_time":0.03733759505,"remaining_time":0.02816695767},
{"learn":[5.005569127],"iteration":57,"passed_time":0.03798035816,"remaining_time":0.02750301797},
{"learn":[4.989969032],"iteration":58,"passed_time":0.03881788676,"remaining_time":0.02697514165},
{"learn":[4.976762446],"iteration":59,"passed_time":0.03953050617,"remaining_time":0.02635367078},
{"learn":[4.967222715],"iteration":60,"passed_time":0.04042725098,"remaining_time":0.02584693095},
{"learn":[4.954407599],"iteration":61,"passed_time":0.04178208207,"remaining_time":0.02560837288},
{"learn":[4.942125056],"iteration":62,"passed_time":0.04258769691,"remaining_time":0.025011822},
{"learn":[4.930230716],"iteration":63,"passed_time":0.04328811971,"remaining_time":0.02434956734},
{"learn":[4.921695642],"iteration":64,"passed_time":0.04402279452,"remaining_time":0.02370458167},
{"learn":[4.906405625],"iteration":65,"passed_time":0.04476400739,"remaining_time":0.02306024623},
{"learn":[4.894330248],"iteration":66,"passed_time":0.04540540431,"remaining_time":0.02236385585},
{"learn":[4.88211557],"iteration":67,"passed_time":0.04620865527,"remaining_time":0.02174524954},
{"learn":[4.877946398],"iteration":68,"passed_time":0.04706447053,"remaining_time":0.02114490705},
{"learn":[4.863182126],"iteration":69,"passed_time":0.04780675496,"remaining_time":0.02048860927},
{"learn":[4.84646533],"iteration":70,"passed_time":0.04844903226,"remaining_time":0.01978904135},
{"learn":[4.838014752],"iteration":71,"passed_time":0.04913735318,"remaining_time":0.01910897068},
{"learn":[4.82981137],"iteration":72,"passed_time":0.04981724581,"remaining_time":0.01842555667},
{"learn":[4.817094767],"iteration":73,"passed_time":0.0504686006,"remaining_time":0.01773221102},
{"learn":[4.808314151],"iteration":74,"passed_time":0.05108793865,"remaining_time":0.01702931288},
{"learn":[4.796235023],"iteration":75,"passed_time":0.05172504147,"remaining_time":0.01633422362},
{"learn":[4.784434534],"iteration":76,"passed_time":0.05237065515,"remaining_time":0.01564318271},
{"learn":[4.774402487],"iteration":77,"passed_time":0.05305895087,"remaining_time":0.01496534512},
{"learn":[4.76731896],"iteration":78,"passed_time":0.05375251145,"remaining_time":0.01428864228},
{"learn":[4.75934113],"iteration":79,"passed_time":0.0544224914,"remaining_time":0.01360562285},
{"learn":[4.754106378],"iteration":80,"passed_time":0.05523577931,"remaining_time":0.01295654083},
{"learn":[4.744002932],"iteration":81,"passed_time":0.05590273662,"remaining_time":0.01227133243},
{"learn":[4.731700554],"iteration":82,"passed_time":0.05657653702,"remaining_time":0.01158796541},
{"learn":[4.723284153],"iteration":83,"passed_time":0.05725752469,"remaining_time":0.01090619518},
{"learn":[4.712232782],"iteration":84,"passed_time":0.05796187049,"remaining_time":0.01022856538},
{"learn":[4.703046867],"iteration":85,"passed_time":0.05866868708,"remaining_time":0.009550716502},
{"learn":[4.698601855],"iteration":86,"passed_time":0.05935121475,"remaining_time":0.008868572319},
{"learn":[4.692429407],"iteration":87,"passed_time":0.05998413645,"remaining_time":0.00817965497},
{"learn":[4.675027364],"iteration":88,"passed_time":0.06065849133,"remaining_time":0.007497116905},
{"learn":[4.662368584],"iteration":89,"passed_time":0.06134145092,"remaining_time":0.006815716769},
{"learn":[4.646206172],"iteration":90,"passed_time":0.06205438841,"remaining_time":0.006137247205},
{"learn":[4.641245848],"iteration":91,"passed_time":0.06279764621,"remaining_time":0.005460664888},
{"learn":[4.633900435],"iteration":92,"passed_time":0.06354483658,"remaining_time":0.004782944689},
{"learn":[4.624738236],"iteration":93,"passed_time":0.06427088842,"remaining_time":0.004102397133},
{"learn":[4.612798287],"iteration":94,"passed_time":0.06489808117,"remaining_time":0.003415688483},
{"learn":[4.605222001],"iteration":95,"passed_time":0.06554777081,"remaining_time":0.002731157117},
{"learn":[4.601725912],"iteration":96,"passed_time":0.06619021063,"remaining_time":0.002047119916},
{"learn":[4.59722371],"iteration":97,"passed_time":0.0668091124,"remaining_time":0.001363451273},
{"learn":[4.580235665],"iteration":98,"passed_time":0.06745922962,"remaining_time":0.0006814063598},
{"learn":[4.57591791],"iteration":99,"passed_time":0.06812872985,"remaining_time":0}
]}